CoolDB/AsyncDataBaseRequests.py
CoolDB/SyncDataBaseRequests.py
CoolDB/__init__.py
cooldb-0.2.dist-info/METADATA
cooldb-0.2.dist-info/WHEEL
cooldb-0.2.dist-info/licenses/LICENSE
cooldb-0.2.dist-info/RECORD
