Metadata-Version: 2.1
Name: CoolDB
Version: 0.2
Summary: CoolDB - это модуль для удобного использования баз данных, таких как sqlite3 и aiosqlite - для синхронного и асинхронного взаимодействия с базами данных
Project-URL: Homepage, https://github.com/enelfo/CoolDB
Project-URL: Issues, https://github.com/enelfo/CoolDB/issues
Author-email: enelfo <enelfo0911@gmail.com>
License-File: LICENSE
Classifier: License :: OSI Approved :: MIT License
Classifier: Operating System :: OS Independent
Classifier: Programming Language :: Python :: 3
Requires-Python: >=3.10
